[
 {
  "allow_items_not_in_stock": 0,
  "allow_non_website_items_in_cart_quotation": 0,
  "company": "Gestão Empresarial",
  "default_customer_group": "All Customer Groups",
  "docstatus": 0,
  "doctype": "Webshop Settings",
  "enable_attribute_filters": 0,
  "enable_checkout": 0,
  "enable_field_filters": 1,
  "enable_recommendations": 0,
  "enable_reviews": 0,
  "enable_variants": 1,
  "enable_wishlist": 0,
  "enabled": 1,
  "filter_attributes": [],
  "filter_fields": [],
  "hide_price_for_guest": 0,
  "hide_variants": 0,
  "is_redisearch_enabled": 0,
  "is_redisearch_loaded": 0,
  "login_required_to_view_products": 0,
  "modified": "2026-03-03 14:55:36.899293",
  "name": "Webshop Settings",
  "payment_gateway_account": null,
  "payment_success_url": "Orders",
  "price_list": "Preço Varejo",
  "products_per_page": 9,
  "quotation_series": "SAL-QTN-.YYYY.-",
  "redirect_on_action": null,
  "save_quotations_as_draft": 0,
  "search_index_fields": null,
  "show_apply_coupon_code_in_website": 0,
  "show_attachments": 0,
  "show_contact_us_button": 0,
  "show_price": 1,
  "show_price_in_quotation": 0,
  "show_quantity_in_website": 1,
  "show_stock_availability": 1,
  "slideshow": null
 }
]